Metadata-Version: 2.4
Name: getstream-plugins-elevenlabs
Version: 0.1.0
Summary: ElevenLabs plugin for GetStream
License-Expression: MIT
Requires-Python: >=3.10
Requires-Dist: elevenlabs>=2.5.0
Requires-Dist: getstream-plugins-common
Requires-Dist: getstream[webrtc]
